LICENSE
README.md
setup.py
temescal/__init__.py
temescal.egg-info/PKG-INFO
temescal.egg-info/SOURCES.txt
temescal.egg-info/dependency_links.txt
temescal.egg-info/requires.txt
temescal.egg-info/top_level.txt