Metadata-Version: 2.1
Name: temescal
Version: 0.5
Summary: Python API for controlling LG speakers
Home-page: http://github.com/google/python-temescal
Author: Matthew Garrett
Author-email: mjg59@google.com
License: UNKNOWN
Platform: UNKNOWN
Classifier: Development Status :: 4 - Beta
Classifier: Intended Audience :: Developers
Classifier: License :: OSI Approved :: Apache Software License
Classifier: Operating System :: OS Independent
Classifier: Programming Language :: Python
License-File: LICENSE
